[
  {
      "domain": ".linkedin.com",
      "expirationDate": 1750947768.43346,
      "hostOnly": false,
      "httpOnly": false,
      "name": "__ssid",
      "path": "/",
      "sameSite": "unspecified",
      "secure": false,
      "session": false,
      "storeId": "0",
      "value": "9e7b00a6-4aed-4994-b1e1-be0083bf0de6",
      "id": 1
  },
  {
      "domain": ".linkedin.com",
      "expirationDate": 1728667354,
      "hostOnly": false,
      "httpOnly": false,
      "name": "_gcl_au",
      "path": "/",
      "sameSite": "unspecified",
      "secure": false,
      "session": false,
      "storeId": "0",
      "value": "1.1.1532949802.1720891355",
      "id": 2
  },
  {
      "domain": ".linkedin.com",
      "expirationDate": 1728667367.380751,
      "hostOnly": false,
      "httpOnly": false,
      "name": "_guid",
      "path": "/",
      "sameSite": "no_restriction",
      "secure": true,
      "session": false,
      "storeId": "0",
      "value": "2a34a8c8-9461-4d6c-b3cb-bec9ee1955d8",
      "id": 3
  },
  {
      "domain": ".linkedin.com",
      "expirationDate": 1723483469,
      "hostOnly": false,
      "httpOnly": false,
      "name": "aam_uuid",
      "path": "/",
      "sameSite": "unspecified",
      "secure": false,
      "session": false,
      "storeId": "0",
      "value": "88276379285056560360349346369114254130",
      "id": 4
  },
  {
      "domain": ".linkedin.com",
      "expirationDate": 1736443368,
      "hostOnly": false,
      "httpOnly": false,
      "name": "AMCV_14215E3D5995C57C0A495C55%40AdobeOrg",
      "path": "/",
      "sameSite": "unspecified",
      "secure": false,
      "session": false,
      "storeId": "0",
      "value": "-637568504%7CMCIDTS%7C19918%7CMCMID%7C88127691106976197590294439968033626361%7CMCAAMLH-1721496168%7C6%7CMCAAMB-1721496168%7CRKhpRz8krg2tLO6pguXWp5olkAcUniQYPHaMWWgdJ3xzPWQmdj0y%7CMCOPTOUT-1720898568s%7CNONE%7CvVersion%7C5.1.1%7CMCCIDH%7C-1591877084",
      "id": 5
  },
  {
      "domain": ".linkedin.com",
      "hostOnly": false,
      "httpOnly": false,
      "name": "AMCVS_14215E3D5995C57C0A495C55%40AdobeOrg",
      "path": "/",
      "sameSite": "unspecified",
      "secure": false,
      "session": true,
      "storeId": "0",
      "value": "1",
      "id": 6
  },
  {
      "domain": ".linkedin.com",
      "expirationDate": 1723483367.570172,
      "hostOnly": false,
      "httpOnly": false,
      "name": "AnalyticsSyncHistory",
      "path": "/",
      "sameSite": "no_restriction",
      "secure": true,
      "session": false,
      "storeId": "0",
      "value": "AQKs6Lv4SX-2vgAAAZCtHlt2N-9i_Rhq8QS86-jJh1qa-41c5tk6xTAaGrYE5ZzHeDWxa68ssYBzc9pAoPB1fw",
      "id": 7
  },
  {
      "domain": ".linkedin.com",
      "expirationDate": 1752427661.153327,
      "hostOnly": false,
      "httpOnly": false,
      "name": "bcookie",
      "path": "/",
      "sameSite": "no_restriction",
      "secure": true,
      "session": false,
      "storeId": "0",
      "value": "\"v=2&11dfc088-1406-44db-87a4-659f6c8dcc17\"",
      "id": 8
  },
  {
      "domain": ".linkedin.com",
      "expirationDate": 1738495786.207328,
      "hostOnly": false,
      "httpOnly": true,
      "name": "dfpfpt",
      "path": "/",
      "sameSite": "lax",
      "secure": true,
      "session": false,
      "storeId": "0",
      "value": "02b72f88d9e24bfe86d491b4d896ed1d",
      "id": 9
  },
  {
      "domain": ".linkedin.com",
      "hostOnly": false,
      "httpOnly": true,
      "name": "fptctx2",
      "path": "/",
      "sameSite": "lax",
      "secure": true,
      "session": true,
      "storeId": "0",
      "value": "taBcrIH61PuCVH7eNCyH0I1otfYAPn9VOPY9aMX8tO3eyd8fBMMmJ9oy7fsssqM6TqkkDUlhfdX%252bk66N8OhtXDIXzBbuhSAczWgPoA9djxWnaNskcxOGvucGZLmm4z2OaUblG5xwHXJJ%252bLVNC9yNdI2NsYbpK%252biWdxia7e%252fl%252bz0uUR96SYEyQ2x3XtHK1%252f14LM8uhvqUY6enp3bApW0x%252ffggKBoD5P2p8ERGc3ppM6GfHgYOL0a0KroNvvsTZianQ23fcp38TdBDxNgFwGODB5jLqijINGzZFqB%252f7HBAAfPW75G2JUZsFHXiRZxv7phSmNx%252bZU7Q7QaOx%252b%252bAOifhAZO8ROo%252fP714rUYsy4TZsmE%253d",
      "id": 10
  },
  {
      "domain": ".linkedin.com",
      "hostOnly": false,
      "httpOnly": false,
      "name": "lang",
      "path": "/",
      "sameSite": "no_restriction",
      "secure": true,
      "session": true,
      "storeId": "0",
      "value": "v=2&lang=en-us",
      "id": 11
  },
  {
      "domain": ".linkedin.com",
      "expirationDate": 1729582487.593433,
      "hostOnly": false,
      "httpOnly": false,
      "name": "li_gc",
      "path": "/",
      "sameSite": "no_restriction",
      "secure": true,
      "session": false,
      "storeId": "0",
      "value": "MTsyMTsxNzE0MDMwNDg2OzI7MDIxVb4++UtKDpxLxVSFlxZ9QDSNZXsNOucj3w+PxVFcRKA=",
      "id": 12
  },
  {
      "domain": ".linkedin.com",
      "expirationDate": 1736443362.284405,
      "hostOnly": false,
      "httpOnly": false,
      "name": "li_mc",
      "path": "/",
      "sameSite": "no_restriction",
      "secure": true,
      "session": false,
      "storeId": "0",
      "value": "MTsyMTsxNzIwODkxMzYwOzI7MDIxpBhhV0BHqN4lFgKEbDT+n7SyrUVEmB92uXJUlD8A1SQ=",
      "id": 13
  },
  {
      "domain": ".linkedin.com",
      "expirationDate": 1728667661.153205,
      "hostOnly": false,
      "httpOnly": false,
      "name": "li_sugr",
      "path": "/",
      "sameSite": "no_restriction",
      "secure": true,
      "session": false,
      "storeId": "0",
      "value": "bb684c9f-c5a0-479d-ae03-611c9677c1d0",
      "id": 14
  },
  {
      "domain": ".linkedin.com",
      "expirationDate": 1728667462.779413,
      "hostOnly": false,
      "httpOnly": false,
      "name": "liap",
      "path": "/",
      "sameSite": "no_restriction",
      "secure": true,
      "session": false,
      "storeId": "0",
      "value": "true",
      "id": 15
  },
  {
      "domain": ".linkedin.com",
      "expirationDate": 1720977762.554867,
      "hostOnly": false,
      "httpOnly": false,
      "name": "lidc",
      "path": "/",
      "sameSite": "no_restriction",
      "secure": true,
      "session": false,
      "storeId": "0",
      "value": "\"b=TB26:s=T:r=T:a=T:p=T:g=5602:u=1149:x=1:i=1720891660:t=1720977760:v=2:sig=AQFEzL_EElogh9GCgidXV7xXVzOuPP0x\"",
      "id": 16
  },
  {
      "domain": ".linkedin.com",
      "expirationDate": 1723483367.840881,
      "hostOnly": false,
      "httpOnly": false,
      "name": "lms_ads",
      "path": "/",
      "sameSite": "no_restriction",
      "secure": true,
      "session": false,
      "storeId": "0",
      "value": "AQGMLI_B70dh3gAAAZCtHlySpUfGLOATKiXCply5N1VcaRM7OJA_gZ96MfZHT5EjlL_y31KUqJfd_V6Rusly8s7azlAp4gEK",
      "id": 17
  },
  {
      "domain": ".linkedin.com",
      "expirationDate": 1723483367.840966,
      "hostOnly": false,
      "httpOnly": false,
      "name": "lms_analytics",
      "path": "/",
      "sameSite": "no_restriction",
      "secure": true,
      "session": false,
      "storeId": "0",
      "value": "AQGMLI_B70dh3gAAAZCtHlySpUfGLOATKiXCply5N1VcaRM7OJA_gZ96MfZHT5EjlL_y31KUqJfd_V6Rusly8s7azlAp4gEK",
      "id": 18
  },
  {
      "domain": ".linkedin.com",
      "hostOnly": false,
      "httpOnly": false,
      "name": "sdsc",
      "path": "/",
      "sameSite": "no_restriction",
      "secure": true,
      "session": true,
      "storeId": "0",
      "value": "1%3A1SZM1shxDNbLt36wZwCgPgvN58iw%3D",
      "id": 19
  },
  {
      "domain": ".linkedin.com",
      "expirationDate": 1723483660,
      "hostOnly": false,
      "httpOnly": false,
      "name": "UserMatchHistory",
      "path": "/",
      "sameSite": "no_restriction",
      "secure": true,
      "session": false,
      "storeId": "0",
      "value": "AQLAwwNvHyvZrAAAAZCtItJCvef83fPOBHu1HQPTYMMc9o3qLM9x51w5YOjICSwfbaMRK5MoHANONKwyHeUVkH3pKkQPu5fQpAKMLtxTvP6LUzLVWD0bMFO42P1PcIHmYf7zJz7TqQyqqnbFN3nsZG1_rN3xQybiwuCms1XEJ_nv4wb5DsL9ZrX-NbAtvJsrsgRqex4iaYUrU3ipG0iGgEm753jB-zBDIxj6Ws55P-BoU5I_QPIqj1BTk44vIM5w_Tr-8-jIBzuNKUpQUHMIbEZMW1dmXQ2auxVfYLsBNWCF3G7X5gBbu-zK5on4pX0pBS1d4eNBOEf45Weeyh4pBvT8AjRHMbEUCeYr2oC7vt0Cw-iHfw",
      "id": 20
  },
  {
      "domain": ".linkedin.com",
      "expirationDate": 1755451394.495867,
      "hostOnly": false,
      "httpOnly": false,
      "name": "visit",
      "path": "/",
      "sameSite": "no_restriction",
      "secure": true,
      "session": false,
      "storeId": "0",
      "value": "v=1&M",
      "id": 21
  },
  {
      "domain": ".www.linkedin.com",
      "expirationDate": 1752427463.075515,
      "hostOnly": false,
      "httpOnly": true,
      "name": "bscookie",
      "path": "/",
      "sameSite": "no_restriction",
      "secure": true,
      "session": false,
      "storeId": "0",
      "value": "\"v=1&2023052115083859e5db43-7d3a-41c3-880c-abb3c2cd5792AQHUVJ11wWg7a06cOz3CEabc9TIHNdDF\"",
      "id": 22
  },
  {
      "domain": ".www.linkedin.com",
      "expirationDate": 1728667462.77947,
      "hostOnly": false,
      "httpOnly": false,
      "name": "JSESSIONID",
      "path": "/",
      "sameSite": "no_restriction",
      "secure": true,
      "session": false,
      "storeId": "0",
      "value": "\"ajax:2483098358703115287\"",
      "id": 23
  },
  {
      "domain": ".www.linkedin.com",
      "expirationDate": 1752427462.779446,
      "hostOnly": false,
      "httpOnly": true,
      "name": "li_at",
      "path": "/",
      "sameSite": "no_restriction",
      "secure": true,
      "session": false,
      "storeId": "0",
      "value": "AQEDATH3azoBa_iAAAABkK0fzyIAAAGQ0SxTIk4AQK3XOMozr0nUI0iDswnWKzfBraXsPOznRr5GK6BfNPAsS-lxUhY_h2OduZ57C8f4z3XzBvB8Fqr-zmaENsr1LrZrVsK9pN7aG7lF6Uhj9I7uLieh",
      "id": 24
  },
  {
      "domain": ".www.linkedin.com",
      "expirationDate": 1752427462.779235,
      "hostOnly": false,
      "httpOnly": true,
      "name": "li_rm",
      "path": "/",
      "sameSite": "no_restriction",
      "secure": true,
      "session": false,
      "storeId": "0",
      "value": "AQF4n90R1ZYsoAAAAYny-a-fb-TLgBVkuDj59EriipbJDrG8pRu-tOnv3Y3nWGKYM_W5CgaweJdU-VfnwkfbhHZ6agD_C7n8iBlNF3Oe62U0Pue_aVXjAqTSUvBDfoZo9vnAEykgF-Q59CvRl5oa9mK8LYa8Gotogj0IuHevJ-VHH2iULgqcwfo1C9iDQZaJjzQD2Cplr29oCjvxA0kURavgTNzVdRn8kWqVf4mQYdjsY4f5tTN4amBRhe5KkCk49eRdOfEyfpzZpDhMAkyhuZclx8TrG95goNba6UzSzBS_K7u4ygpwHC5hDXStOjjzBSabsfUil0XpGzH5Q0g",
      "id": 25
  },
  {
      "domain": ".www.linkedin.com",
      "expirationDate": 1736447258,
      "hostOnly": false,
      "httpOnly": false,
      "name": "li_theme",
      "path": "/",
      "sameSite": "unspecified",
      "secure": true,
      "session": false,
      "storeId": "0",
      "value": "light",
      "id": 26
  },
  {
      "domain": ".www.linkedin.com",
      "expirationDate": 1736447258,
      "hostOnly": false,
      "httpOnly": false,
      "name": "li_theme_set",
      "path": "/",
      "sameSite": "unspecified",
      "secure": true,
      "session": false,
      "storeId": "0",
      "value": "app",
      "id": 27
  },
  {
      "domain": ".www.linkedin.com",
      "expirationDate": 1722101258,
      "hostOnly": false,
      "httpOnly": false,
      "name": "timezone",
      "path": "/",
      "sameSite": "unspecified",
      "secure": true,
      "session": false,
      "storeId": "0",
      "value": "Europe/Paris",
      "id": 28
  },
  {
      "domain": "www.linkedin.com",
      "expirationDate": 1736443357,
      "hostOnly": true,
      "httpOnly": false,
      "name": "g_state",
      "path": "/",
      "sameSite": "unspecified",
      "secure": false,
      "session": false,
      "storeId": "0",
      "value": "{\"i_l\":0}",
      "id": 29
  },
  {
      "domain": "www.linkedin.com",
      "expirationDate": 1752427400,
      "hostOnly": true,
      "httpOnly": false,
      "name": "li_alerts",
      "path": "/",
      "sameSite": "no_restriction",
      "secure": true,
      "session": false,
      "storeId": "0",
      "value": "e30=",
      "id": 30
  },
  {
      "domain": "www.linkedin.com",
      "expirationDate": 1720894994.495641,
      "hostOnly": true,
      "httpOnly": false,
      "name": "li_g_recent_logout",
      "path": "/",
      "sameSite": "unspecified",
      "secure": false,
      "session": false,
      "storeId": "0",
      "value": "v=1&true",
      "id": 31
  },
  {
      "domain": "www.linkedin.com",
      "hostOnly": true,
      "httpOnly": false,
      "name": "lil-lang",
      "path": "/",
      "sameSite": "no_restriction",
      "secure": true,
      "session": true,
      "storeId": "0",
      "value": "en_US",
      "id": 32
  },
  {
      "domain": "www.linkedin.com",
      "hostOnly": true,
      "httpOnly": false,
      "name": "PLAY_LANG",
      "path": "/",
      "sameSite": "unspecified",
      "secure": false,
      "session": true,
      "storeId": "0",
      "value": "fr",
      "id": 33
  },
  {
      "domain": "www.linkedin.com",
      "hostOnly": true,
      "httpOnly": true,
      "name": "PLAY_SESSION",
      "path": "/",
      "sameSite": "lax",
      "secure": true,
      "session": true,
      "storeId": "0",
      "value": "eyJhbGciOiJIUzI1NiJ9.eyJkYXRhIjp7ImFjY291bnQuY2xvc2UucHJlY29uZGl0aW9uLnNlc3Npb24ua2V5IjoiYWNjb3VudC5jbG9zZS5wcmVjb25kaXRpb24udmFsdWUucGFzc2VkdXJuOmxpOm1lbWJlcjoxMjE4NTMzMzU0Iiwic2Vzc2lvbl9pZCI6IjUxOTEzMTQ4LTYzNWMtNDZlOC05NmZhLTQ2MTViNjMxYjhlN3wxNzIwNzE4OTYwIiwiYWxsb3dsaXN0Ijoie30iLCJyZWNlbnRseS1zZWFyY2hlZCI6IiIsInJlZmVycmFsLXVybCI6Imh0dHBzOi8vd3d3LmxpbmtlZGluLmNvbS9oZWxwL2xpbmtlZGluL2Fuc3dlci9hMTM3OTA2NCIsInJlY2VudGx5LXZpZXdlZCI6IiIsIkNQVC1pZCI6Ilx1MDAxM0fDhyEzS8O7LsKzw7bDlDbDm01cdTAwMDZoIiwiYWNjb3VudC5jbG9zZS5zdWNjZXNzLmtleSI6ImFjY291bnQuY2xvc2Uuc3VjY2VzcyIsImZsb3dUcmFja2luZ0lkIjoiVitCODRBMWJTN2lOL0hoalZUdjhOZz09IiwiZXhwZXJpZW5jZSI6IiIsInRyayI6IiJ9LCJuYmYiOjE3MjA3MTk2NDksImlhdCI6MTcyMDcxOTY0OX0.xHIYWxGCIGBymr-f_xpiWV64rFQL1bbdeYpaEEHYPmw",
      "id": 34
  }
  ]
